demos/__init__.py
demos/demo_image.py
demos/demo_selector.py
demos/synthetic_signals.py
examples/__init__.py
examples/convergence_control.py
examples/minibatch_algorithms.py
examples/shift_invariant_decomposition.py
logos/__init__.py
logos/tnmf_header.pdf
logos/tnmf_header.png
logos/tnmf_header.svg
logos/tnmf_logo.pdf
logos/tnmf_logo.png
logos/tnmf_logo.svg
scripts/__init__.py
scripts/tnmf.py
tnmf/TransformInvariantNMF.py
tnmf/__init__.py
tnmf/_version.py
tnmf/backends/NumPy.py
tnmf/backends/NumPy_CachingFFT.py
tnmf/backends/NumPy_FFT.py
tnmf/backends/PyTorch.py
tnmf/backends/PyTorch_FFT.py
tnmf/backends/_Backend.py
tnmf/backends/_NumPyBackend.py
tnmf/backends/_NumPyFFTBackend.py
tnmf/backends/_PyTorchBackend.py
tnmf/backends/__init__.py
tnmf/tests/__init__.py
tnmf/tests/test_1d.py
tnmf/tests/test_backends.py
tnmf/tests/test_demos.py
tnmf/tests/test_examples.py
tnmf/tests/test_init.py
tnmf/tests/test_minibatch.py
tnmf/tests/test_sparsity_inhibition.py
tnmf/tests/test_stream.py
tnmf/utils/__init__.py
tnmf/utils/data_loading.py
tnmf/utils/demo.py
tnmf/utils/signals.py
tnmf-0.2.0.dist-info/LICENSE
tnmf-0.2.0.dist-info/METADATA
tnmf-0.2.0.dist-info/WHEEL
tnmf-0.2.0.dist-info/entry_points.txt
tnmf-0.2.0.dist-info/top_level.txt
tnmf-0.2.0.dist-info/RECORD
