Metadata-Version: 2.1
Name: tnmf
Version: 0.2.0
Summary: Transform-Invariant Non-Negative Matrix Factorization
Home-page: https://github.com/emdgroup/tnmf
Author: Adrian Šošić, Mathias Winkel
Author-email: adrian.sosic@merckgroup.com, mathias.winkel@merckgroup.com
License: Apache License, Version 2.0
Project-URL: Documentation, https://emdgroup.github.io/tnmf/
Project-URL: Bug Tracker, https://github.com/emdgroup/tnmf/issues
Platform: any
Classifier: Programming Language :: Python :: 3
Classifier: Programming Language :: Python :: 3.7
Classifier: Programming Language :: Python :: 3.8
Classifier: Programming Language :: Python :: 3.9
Classifier: Operating System :: OS Independent
Classifier: License :: OSI Approved :: Apache Software License
Requires-Python: >=3.7
License-File: LICENSE
Requires-Dist: matplotlib (>=3.3.3)
Requires-Dist: more-itertools (>=8.6.0)
Requires-Dist: numpy (>=1.19.4)
Requires-Dist: opt-einsum (>=3.3.0)
Requires-Dist: scipy (>=1.5.4)
Requires-Dist: streamlit (>=0.84.0)
Requires-Dist: torch (>=1.8.1)
